collective.z3cform.datagridfield-3.0.4-py3.13-nspkg.pth
collective/z3cform/datagridfield/__init__.py
collective/z3cform/datagridfield/autoform.py
collective/z3cform/datagridfield/blockdatagridfield.py
collective/z3cform/datagridfield/configure.zcml
collective/z3cform/datagridfield/converters.py
collective/z3cform/datagridfield/datagridfield.py
collective/z3cform/datagridfield/datagridfield_display.pt
collective/z3cform/datagridfield/datagridfield_input.pt
collective/z3cform/datagridfield/datagridfield_input_block.pt
collective/z3cform/datagridfield/datagridfieldobject_display.pt
collective/z3cform/datagridfield/datagridfieldobject_input.pt
collective/z3cform/datagridfield/datagridfieldobject_input_block.pt
collective/z3cform/datagridfield/deserializer.py
collective/z3cform/datagridfield/interfaces.py
collective/z3cform/datagridfield/overrides.zcml
collective/z3cform/datagridfield/profiles.zcml
collective/z3cform/datagridfield/registry.py
collective/z3cform/datagridfield/row.py
collective/z3cform/datagridfield/setuphandlers.py
collective/z3cform/datagridfield/supermodel.py
collective/z3cform/datagridfield/testing.py
collective/z3cform/datagridfield/demo/__init__.py
collective/z3cform/datagridfield/demo/behavior.py
collective/z3cform/datagridfield/demo/configure.zcml
collective/z3cform/datagridfield/demo/content.py
collective/z3cform/datagridfield/demo/dgftest.xml
collective/z3cform/datagridfield/demo/editform.pt
collective/z3cform/datagridfield/demo/editform_object.py
collective/z3cform/datagridfield/demo/editform_simple.py
collective/z3cform/datagridfield/demo/interfaces.py
collective/z3cform/datagridfield/demo/menu.pt
collective/z3cform/datagridfield/demo/profile/types.xml
collective/z3cform/datagridfield/demo/profile/types/DGFTest.xml
collective/z3cform/datagridfield/demo/profile/types/Document.xml
collective/z3cform/datagridfield/locales/README.rst
collective/z3cform/datagridfield/locales/collective.z3cform.datagridfield.pot
collective.z3cform.datagridfield-3.0.4.dist-info/METADATA
collective.z3cform.datagridfield-3.0.4.dist-info/WHEEL
collective.z3cform.datagridfield-3.0.4.dist-info/entry_points.txt
collective.z3cform.datagridfield-3.0.4.dist-info/namespace_packages.txt
collective.z3cform.datagridfield-3.0.4.dist-info/top_level.txt
collective.z3cform.datagridfield-3.0.4.dist-info/RECORD
