Metadata-Version: 2.2
Name: collective.z3cform.datagridfield
Version: 3.0.4
Summary: Fields with repeatable data grid (table-like) for z3.cform
Home-page: https://github.com/collective/collective.z3cform.datagridfield
Author: Kevin Gill
Author-email: kevin@movieextras.se
License: GPLv2
Keywords: plone z3cform table data grid
Classifier: Development Status :: 5 - Production/Stable
Classifier: Environment :: Web Environment
Classifier: Framework :: Plone
Classifier: Framework :: Plone :: Addon
Classifier: Framework :: Plone :: 6.0
Classifier: License :: OSI Approved :: GNU General Public License v2 (GPLv2)
Classifier: Operating System :: OS Independent
Classifier: Programming Language :: JavaScript
Classifier: Programming Language :: Python
Classifier: Programming Language :: Python :: 3.8
Classifier: Programming Language :: Python :: 3.9
Classifier: Programming Language :: Python :: 3.10
Classifier: Programming Language :: Python :: 3.11
Classifier: Topic :: Software Development :: Libraries :: Python Modules
Requires-Python: >=3.8
Requires-Dist: Products.GenericSetup
Requires-Dist: plone.app.dexterity
Requires-Dist: plone.app.z3cform
Requires-Dist: plone.autoform
Requires-Dist: plone.base
Requires-Dist: plone.dexterity
Requires-Dist: plone.restapi
Requires-Dist: plone.supermodel
Requires-Dist: setuptools
Requires-Dist: z3c.form>=4.0
Provides-Extra: test
Requires-Dist: plone.testing; extra == "test"
Requires-Dist: plone.app.testing; extra == "test"
Requires-Dist: plone.app.robotframework[debug]; extra == "test"
Requires-Dist: robotsuite; extra == "test"
Requires-Dist: robotframework-browser; extra == "test"
Dynamic: author
Dynamic: author-email
Dynamic: classifier
Dynamic: description
Dynamic: home-page
Dynamic: keywords
Dynamic: license
Dynamic: provides-extra
Dynamic: requires-dist
Dynamic: requires-python
Dynamic: summary
